wpy/__init__.py
wpy/base.py
wpy/echo.py
wpy/format.py
wpy/functools.py
wpy/hashs.py
wpy/id.py
wpy/json.py
wpy/lists.py
wpy/path.py
wpy/randoms.py
wpy/security.py
wpy/waiting.py
wpy/api/__init__.py
wpy/api/async_api_client.py
wpy/app/main.py
wpy/cli/__init__.py
wpy/cli/shell.py
wpy/common/__init__.py
wpy/common/enum.py
wpy/common/loggers.py
wpy/common/rand.py
wpy/common/security.py
wpy/common/singleton.py
wpy/common/xml.py
wpy/completion/__init__.py
wpy/completion/base.py
wpy/completion/command.py
wpy/completion/filesystem.py
wpy/completion/word.py
wpy/db/file_storage.py
wpy/downloader/__init__.py
wpy/downloader/download.py
wpy/process/__init__.py
wpy/process/downloader.py
wpy/process/multiprocess.py
wpy/shell/__init__.py
wpy/shell/base.py
wpy/shell/command.py
wpy/shell/errors.py
wpy-0.7.7.dist-info/METADATA
wpy-0.7.7.dist-info/WHEEL
wpy-0.7.7.dist-info/entry_points.txt
wpy-0.7.7.dist-info/licenses/LICENSE
wpy-0.7.7.dist-info/RECORD
