Metadata-Version: 2.4
Name: wpy
Version: 0.7.7
Summary: a library for python Developer
Author-email: wxnacy <wxnacy@gmail.com>
License: MIT
License-File: LICENSE
Requires-Python: >=3.11
Requires-Dist: aiohttp>=3.11.7
Requires-Dist: pydantic>=2.10.1
Requires-Dist: requests>=2.32.3
Provides-Extra: dev
Requires-Dist: pytest-asyncio>=0.25.3; extra == 'dev'
Requires-Dist: pytest-cov>=3.0.0; extra == 'dev'
Requires-Dist: pytest-html>=3.1.1; extra == 'dev'
Requires-Dist: pytest>=8.3.3; extra == 'dev'
Requires-Dist: sphinx-rtd-theme>=1.0.0; extra == 'dev'
Requires-Dist: sphinx>=4.5.0; extra == 'dev'
